MANIFEST.in
README.md
setup.py
dash_grid_layout/__init__.py
dash_grid_layout/bundle.js
dash_grid_layout/bundle.js.map
dash_grid_layout/metadata.json
dash_grid_layout/version.py
dash_grid_layout.egg-info/PKG-INFO
dash_grid_layout.egg-info/SOURCES.txt
dash_grid_layout.egg-info/dependency_links.txt
dash_grid_layout.egg-info/top_level.txt