Metadata-Version: 1.0
Name: dash-grid-layout
Version: 1.0.5
Summary: Dash UI Component for using the React Grid Layout library
Home-page: UNKNOWN
Author: FlightDataServices
Author-email: UNKNOWN
License: MIT
Platform: UNKNOWN
